_delb/__init__.py
_delb/exceptions.py
_delb/names.py
_delb/nodes.py
_delb/parser.py
_delb/py.typed
_delb/typing.py
_delb/utils.py
_delb/plugins/__init__.py
_delb/plugins/core_loaders.py
_delb/plugins/https_loader.py
_delb/xpath/__init__.py
_delb/xpath/ast.py
_delb/xpath/functions.py
_delb/xpath/parser.py
_delb/xpath/tokenizer.py
delb/__init__.py
delb/exceptions.py
delb/names.py
delb/nodes.py
delb/parser.py
delb/py.typed
delb/transform.py
delb/typing.py
delb/utils.py
delb-0.5.dist-info/METADATA
delb-0.5.dist-info/WHEEL
delb-0.5.dist-info/entry_points.txt
delb-0.5.dist-info/licenses/LICENSE.txt
delb-0.5.dist-info/RECORD
