Metadata-Version: 2.4
Name: delb
Version: 0.5
Summary: A library that provides an ergonomic model for XML encoded text documents (e.g. with TEI-XML).
Project-URL: Changelog, https://delb.readthedocs.io/latest/changes.html
Project-URL: Documentation, https://delb.readthedocs.io/
Project-URL: Issues, https://github.com/delb-xml/delb-py/issues
Project-URL: Repository, https://github.com/delb-xml/delb-py
Author-email: Frank Sachsenheim <delb-project@posteo.net>
License-Expression: AGPL-3.0-or-later
License-File: LICENSE.txt
Keywords: markup,tei,text processing,xhtml,xml
Classifier: Development Status :: 4 - Beta
Classifier: Intended Audience :: Developers
Classifier: Intended Audience :: Science/Research
Classifier: License :: OSI Approved :: GNU Affero General Public License v3 or later (AGPLv3+)
Classifier: Natural Language :: English
Classifier: Programming Language :: Python :: 3.8
Classifier: Programming Language :: Python :: 3.9
Classifier: Programming Language :: Python :: 3.10
Classifier: Programming Language :: Python :: 3.11
Classifier: Programming Language :: Python :: 3.12
Classifier: Programming Language :: Python :: 3.13
Classifier: Topic :: Text Processing :: Markup :: XML
Requires-Python: >=3.8
Requires-Dist: cssselect
Requires-Dist: importlib-metadata; python_version < '3.10'
Requires-Dist: lxml
Requires-Dist: typing-extensions; python_version < '3.10'
Provides-Extra: https-loader
Requires-Dist: httpx[http2]; extra == 'https-loader'
